hello_my_world/__init__.py
hello_my_world/hello.py
Hello_My_World-0.1.4.dist-info/AUTHORS.md
Hello_My_World-0.1.4.dist-info/LICENSE
Hello_My_World-0.1.4.dist-info/METADATA
Hello_My_World-0.1.4.dist-info/WHEEL
Hello_My_World-0.1.4.dist-info/top_level.txt
Hello_My_World-0.1.4.dist-info/RECORD
