Metadata-Version: 2.1
Name: Hello-My-World
Version: 0.1.4
Summary: A simple package for python
Home-page: UNKNOWN
Author: eocode
Author-email: hola@eliasojedamedina.com
License: MIT License
Project-URL: Homepage, https://github.com/eocode/Hello-My-World
Project-URL: Issue tracker, https://github.com/eocode/Hello-My-World/issues
Project-URL: Code, https://github.com/eocode/Hello-My-World
Project-URL: Documentation, https://github.com/eocode/Hello-My-World/wiki
Platform: UNKNOWN
Classifier: Programming Language :: Python :: 3
Classifier: Operating System :: OS Independent
Requires-Python: >=3.6
